.bzrignore
COPYING
README.txt
automa.wpr
setup.py
automa/__init__.py
automa/configfile.py
automa/log.py
automa/main.py
automa/opts.py
automa/path.py
automa/setup_info.py
automa/shell.py
automa/ssh.py
automa/sysbuilder.py
automa/tasks.py
automa/utils.py
automa/virtual.py
automa.egg-info/PKG-INFO
automa.egg-info/SOURCES.txt
automa.egg-info/dependency_links.txt
automa.egg-info/entry_points.txt
automa.egg-info/requires.txt
automa.egg-info/top_level.txt
automa.egg-info/zip-safe