Metadata-Version: 1.0
Name: automa
Version: 0.1.20
Summary: Scripting automation utility
Home-page: http://pypi.python.org/pypi/automa/
Author: Marco Pantaleoni
Author-email: m.pantaleoni@softwarefabrica.org
License: GNU GPL v2
Keywords: automation build scripting shell
Platform: UNKNOWN
Classifier: Development Status :: 4 - Beta
Classifier: Intended Audience :: Developers
Classifier: License :: OSI Approved :: GNU General Public License (GPL)
Classifier: Operating System :: OS Independent
Classifier: Programming Language :: Python :: 2.4
Classifier: Environment :: Console
